snakespace/__init__.py
snakespace/snakespace.py
snakespace-0.1.12.dist-info/LICENSE
snakespace-0.1.12.dist-info/METADATA
snakespace-0.1.12.dist-info/WHEEL
snakespace-0.1.12.dist-info/top_level.txt
snakespace-0.1.12.dist-info/RECORD
