Metadata-Version: 2.1
Name: snakespace
Version: 0.1.12
Summary: Create strings from attribute chains!
Home-page: https://github.com/cmrfrd/snakespace/
Author: cmrfrd
Author-email: alexanderjcomerford@gmail.com
License: mit
Platform: any
Classifier: Topic :: Utilities
Classifier: Programming Language :: Python
Classifier: Programming Language :: Python :: 3
Classifier: Programming Language :: Python :: 3 :: Only
Classifier: Programming Language :: Python :: 3.6
Classifier: Programming Language :: Python :: 3.7
Classifier: Programming Language :: Python :: 3.8
Classifier: Intended Audience :: Developers
Classifier: License :: OSI Approved :: MIT License
Classifier: Operating System :: POSIX :: Linux
Classifier: Operating System :: Unix
Classifier: Operating System :: MacOS
Classifier: Operating System :: Microsoft :: Windows
